pluginconf/__init__.py
pluginconf/bind.py
pluginconf/depends.py
pluginconf/flit.py
pluginconf/gui.py
pluginconf/setup.py
pluginconf-0.8.0.dist-info/entry_points.txt
pluginconf-0.8.0.dist-info/LICENSE
pluginconf-0.8.0.dist-info/WHEEL
pluginconf-0.8.0.dist-info/METADATA
pluginconf-0.8.0.dist-info/RECORD
