Metadata-Version: 2.1
Name: pluginconf
Version: 0.8.0
Summary: Read meta data, pyz/package contents, module locating
Home-page: https://fossil.include-once.org/pluginspec/wiki/pluginconf
License: PD
Keywords: config
Requires-Python: >= 2.7
Classifier: License :: Public Domain
Classifier: Development Status :: 5 - Production/Stable
Project-URL: Api_Docs, https://fossil.include-once.org/pluginspec/doc/trunk/html/index.html
Project-URL: Docs, https://fossil.include-once.org/pluginspec/
